django_jchart-0.4.2.dist-info/DESCRIPTION.rst
django_jchart-0.4.2.dist-info/METADATA
django_jchart-0.4.2.dist-info/metadata.json
django_jchart-0.4.2.dist-info/RECORD
django_jchart-0.4.2.dist-info/top_level.txt
django_jchart-0.4.2.dist-info/WHEEL
jchart/__init__.py
jchart/apps.py
jchart/config.py
jchart/models.py
jchart/tests.py
jchart/templates/charting/chart.html
jchart/templates/charting/html.html
jchart/templates/charting/js.html
jchart/templates/charting/async/chart.html
jchart/templates/charting/async/html.html
jchart/templates/charting/async/js.html
jchart/templatetags/__init__.py
jchart/templatetags/jchart.py
jchart/views/__init__.py
jchart/views/mixins.py
